pyemblib/__init__.py
pyemblib/common.py
pyemblib/convert.py
pyemblib/get_size.py
pyemblib/get_vocabulary.py
pyemblib/glove.py
pyemblib/test_equality.py
pyemblib/word2vec.py
pyemblib/word2vec_to_text.py
pyemblib-0.1.2.dist-info/LICENSE
pyemblib-0.1.2.dist-info/METADATA
pyemblib-0.1.2.dist-info/WHEEL
pyemblib-0.1.2.dist-info/top_level.txt
pyemblib-0.1.2.dist-info/RECORD
