Metadata-Version: 2.1
Name: pyemblib
Version: 0.1.2
Summary: Lightweight package for reading/writing pre-trained word embedding files
Home-page: http://github.com/drgriffis/pyemblib
Author: Denis Newman-Griffis
Author-email: denis.newman.griffis@gmail.com
License: UNKNOWN
Platform: UNKNOWN
Classifier: Programming Language :: Python :: 3
Classifier: License :: OSI Approved :: MIT License
Classifier: Operating System :: OS Independent
Requires-Dist: numpy
